spback-0.2.7.dist-info/METADATA
spback-0.2.7.dist-info/WHEEL
spback-0.2.7.dist-info/entry_points.txt
spback/__init__.py
spback/basic_/__init__.py
spback/basic_/models/__init__.py
spback/basic_/models/hash.py
spback/basic_/models/soft_delete.py
spback/basic_/views/__init__.py
spback/basic_/views/generic.py
spback/basic_/views/page.py
spback/basic_/views/test_page.py
spback/bulma/__init__.py
spback/bulma/admin.py
spback/bulma/apps.py
spback/bulma/migrations/__init__.py
spback/bulma/mixins.py
spback/bulma/models.py
spback/bulma/templates/bulma/base.html
spback/bulma/templates/bulma/footer.html
spback/bulma/templates/bulma/layout/withside.html
spback/bulma/templates/bulma/libs/header.html
spback/bulma/templates/bulma/libs/sidebar.html
spback/bulma/tests.py
spback/bulma/views.py
spback/commands/__init__.py
spback/commands/user.py
spback/examples/__init__.py
spback/examples/protect_router.py
spback/examples/samples.py
spback/funcs/__init__.py
spback/funcs/test_funcs.py
spback/handler/__init__.py
spback/handler/errors.py
spback/jwt_/__init__.py
spback/jwt_/service.py
spback/jwt_/view.py
spback/logger/__init__.py
spback/logger/create.py
spback/logger/fn.py
spback/logger/handler.py
spback/logger/shortcuts.py
spback/logger/test_handler.py
spback/middleware/__init__.py
spback/middleware/slow.py
spback/mvc/__init__.py
spback/otp/__init__.py
spback/script/__init__.py
spback/script/pwd.py
spback/script/use_django.py
spback/script/user.py
spback/shortcuts.py
spback/srv/__init__.py
spback/srv/errors.py
spback/static/css/bulma.css
spback/static/css/bulma.css.map
spback/static/css/bulma.min.css
spback/types/__init__.py
spback/types/general.py
spback/urls.py
spback/user_/__init__.py
spback/user_/reset.py
spback/user_/service.py
spback/user_/user.py
spback-0.2.7.dist-info/RECORD
