Metadata-Version: 2.1
Name: spback
Version: 0.2.7
Summary: Sun praise internal backend package.
Author-Email: svtter <svtter@qq.com>
License: NOT OPEN SOURCE
Requires-Python: <3.12,>=3.11
Requires-Dist: django<6.0,>3.2
Requires-Dist: colorlog>=6.8.2
Requires-Dist: django-ninja<2.0.0,>=1.2.0
Requires-Dist: django-ninja-extra>=0.20.7
Requires-Dist: django-ninja-jwt>=5.3.4
Requires-Dist: gevent
Requires-Dist: gunicorn
Requires-Dist: celery
Requires-Dist: django-celery-beat
Requires-Dist: django-celery-results
Requires-Dist: django-cors-headers
Requires-Dist: dj-database-url
Requires-Dist: python-dotenv
Requires-Dist: psycopg2-binary
